cosoquehacecosas/__init__.py
cosoquehacecosas/main.py
cosoquehacecosas-0.0.1.dist-info/LICENSE
cosoquehacecosas-0.0.1.dist-info/METADATA
cosoquehacecosas-0.0.1.dist-info/WHEEL
cosoquehacecosas-0.0.1.dist-info/top_level.txt
cosoquehacecosas-0.0.1.dist-info/RECORD
