Metadata-Version: 2.1
Name: cosoquehacecosas
Version: 0.0.1
Summary: cosoquehacecosas test
Home-page: UNKNOWN
Author: netgian
Author-email: <gianlopez1605@gmail.com>
License: UNKNOWN
Platform: UNKNOWN
License-File: LICENSE
